firecracker/__init__.py
firecracker/_version.py
firecracker/api.py
firecracker/config.py
firecracker/exceptions.py
firecracker/logger.py
firecracker/microvm.py
firecracker/network.py
firecracker/process.py
firecracker/scripts.py
firecracker/utils.py
firecracker/vmm.py
firecracker_python-0.0.4.dist-info/LICENSE
firecracker_python-0.0.4.dist-info/METADATA
firecracker_python-0.0.4.dist-info/WHEEL
firecracker_python-0.0.4.dist-info/entry_points.txt
firecracker_python-0.0.4.dist-info/top_level.txt
firecracker_python-0.0.4.dist-info/RECORD
