Metadata-Version: 2.1
Name: firecracker-python
Version: 0.0.4
Summary: A Python client library to interact with Firecracker microVMs
Author: Muhammad Yuga Nugraha
License: MIT License
Classifier: Development Status :: 3 - Alpha
Classifier: Intended Audience :: Developers
Classifier: License :: OSI Approved :: MIT License
Classifier: Programming Language :: Python :: 3
Classifier: Programming Language :: Python :: 3.8
Classifier: Programming Language :: Python :: 3.9
Classifier: Programming Language :: Python :: 3.10
Requires-Python: >=3.8
License-File: LICENSE
Requires-Dist: docker==7.1.0
Requires-Dist: requests==2.32.3
Requires-Dist: requests-unixsocket==0.4.1
Requires-Dist: tenacity==9.0.0
Requires-Dist: psutil==7.0.0
Requires-Dist: pyroute2==0.8.1
Requires-Dist: paramiko==3.5.1
Requires-Dist: faker==37.0.2
